{
  "gitSyncId": "66e92c26ab302c5f2463ffa7_84479661-06db-44f2-8ce7-c408b421f71c",
  "id": "Page1_JSModule11",
  "moduleUUID": "ed229d2a-da47-404d-8a43-98d7b76494f9",
  "packageUUID": "0a7d8857-f707-407c-84bb-9a3823abc85b",
  "type": "JS_MODULE",
  "unpublishedModuleInstance": {
    "contextType": "PAGE",
    "inputs": {
      "myFun1123": "[]",
      "myFun2": "[]"
    },
    "moduleInputs": {
      "fbjdozgclo": {
        "controlType": "INPUT_TEXT",
        "defaultValue": "[]",
        "id": "fbjdozgclo",
        "label": "myFun2",
        "propertyName": "inputs.myFun2"
      },
      "wipdtouidv": {
        "controlType": "INPUT_TEXT",
        "defaultValue": "[]",
        "id": "wipdtouidv",
        "label": "myFun1123",
        "propertyName": "inputs.myFun1"
      }
    },
    "name": "JSModule11",
    "pageId": "Page1",
    "version": "0.0.12"
  }
}